{
  "name": "twitter-post",
  "version": "1.0.0",
  "description": "Post tweets and threads on X (Twitter) via the web interface",
  "author": "cyclop-team",
  "triggers": [
    "tweet",
    "post on twitter",
    "post on x",
    "twitter post",
    "x post"
  ],
  "steps": [
    "Open X (Twitter) at x.com in Chrome or the default browser",
    "Click the Post or compose button",
    "Type the tweet text in the compose area",
    "Optionally add images or videos if requested",
    "Click the Post button to publish",
    "Verify the tweet appears in the feed"
  ],
  "maxIterations": 15,
  "category": "social",
  "tags": ["twitter", "x", "social", "post"],
  "verified": true,
  "permissions": []
}
